CRUDFastAPI/__init__.py
CRUDFastAPI/crud/__init__.py
CRUDFastAPI/crud/fast_crud.py
CRUDFastAPI/crud/helper.py
CRUDFastAPI/endpoint/__init__.py
CRUDFastAPI/endpoint/crud_router.py
CRUDFastAPI/endpoint/endpoint_creator.py
CRUDFastAPI/endpoint/helper.py
CRUDFastAPI/exceptions/__init__.py
CRUDFastAPI/exceptions/http_exceptions.py
CRUDFastAPI/paginated/__init__.py
CRUDFastAPI/paginated/helper.py
CRUDFastAPI/paginated/response.py
CRUDFastAPI/paginated/schemas.py
CRUDFastAPI/py.typed
LICENSE
crudfastapi-0.1.2.dist-info/LICENSE
crudfastapi-0.1.2.dist-info/METADATA
crudfastapi-0.1.2.dist-info/WHEEL
crudfastapi-0.1.2.dist-info/RECORD
