Metadata-Version: 2.1
Name: CRUDFastAPI
Version: 0.1.2
Summary: CRUDFastAPI is a Python package for FastAPI, offering robust async CRUD operations and flexible endpoint creation utilities.
Home-page: https://github.com/mithun2003/CRUDFastAPI
License: MIT
Keywords: fastapi,crud,async,sqlalchemy,pydantic,fastcrud,crudfastapi
Author: Mithun Thomas
Author-email: mithunthomas003@gmail.com
Requires-Python: >=3.9,<4.0
Classifier: Development Status :: 4 - Beta
Classifier: Framework :: FastAPI
Classifier: Intended Audience :: Developers
Classifier: License :: OSI Approved :: MIT License
Classifier: Operating System :: OS Independent
Classifier: Programming Language :: Python :: 3
Classifier: Programming Language :: Python :: 3.9
Classifier: Programming Language :: Python :: 3.10
Classifier: Programming Language :: Python :: 3.11
Classifier: Programming Language :: Python :: 3.12
Classifier: Topic :: Software Development :: Libraries
Classifier: Typing :: Typed
Requires-Dist: SQLAlchemy (>=2.0.0,<3.0.0)
Requires-Dist: SQLAlchemy-Utils (>=0.41.1,<0.42.0)
Requires-Dist: fastapi (>=0.100.0,<0.112.0)
Requires-Dist: pydantic (>=2.0.0,<3.0.0)
Project-URL: Repository, https://github.com/mithun2003/CRUDFastAPI
